bpy_addon_build/__init__.py
bpy_addon_build/api/__init__.py
bpy_addon_build/args.py
bpy_addon_build/build_context/__init__.py
bpy_addon_build/build_context/build.py
bpy_addon_build/build_context/core.py
bpy_addon_build/build_context/hook_definitions.py
bpy_addon_build/build_context/hooks.py
bpy_addon_build/build_context/install.py
bpy_addon_build/built_in_actions/extension.py
bpy_addon_build/config.py
bpy_addon_build/util.py
lib_bpybuild_ext/README.md
lib_bpybuild_ext/__init__.py
lib_bpybuild_ext/compat.py
lib_bpybuild_ext/manifest.py
lib_bpybuild_ext/verify.py
bpy_addon_build-0.5.1.dist-info/LICENSE
bpy_addon_build-0.5.1.dist-info/METADATA
bpy_addon_build-0.5.1.dist-info/WHEEL
bpy_addon_build-0.5.1.dist-info/entry_points.txt
bpy_addon_build-0.5.1.dist-info/RECORD
