Metadata-Version: 2.1
Name: bpy-addon-build
Version: 0.5.1
Summary: A build system to make building and testing Blender addons 10 times easier
Home-page: https://github.com/StandingPadAnimations/bpy-build
License: BSD-3-Clause
Author: Mahid Sheikh
Author-email: mahid@standingpad.org
Requires-Python: >=3.9
Classifier: License :: OSI Approved :: BSD License
Classifier: Programming Language :: Python :: 3
Classifier: Programming Language :: Python :: 3.9
Classifier: Programming Language :: Python :: 3.10
Classifier: Programming Language :: Python :: 3.11
Classifier: Programming Language :: Python :: 3.12
Requires-Dist: attrs (>=23.1.0,<24.0.0)
Requires-Dist: packaging (>=24.1,<25.0)
Requires-Dist: pyyaml (>=6.0.1,<7.0.0)
Requires-Dist: rich (>=13.7.0,<14.0.0)
Requires-Dist: tomli (>=2.0.1,<3.0.0)
Requires-Dist: typeguard (>=4.1.5,<5.0.0)
Requires-Dist: typing-extensions (>=4.11.0,<5.0.0)
